setup.py
dist_udacity/Binomialdistribution.py
dist_udacity/Gaussiandistribution.py
dist_udacity/Generaldistribution.py
dist_udacity/__init__.py
dist_udacity.egg-info/PKG-INFO
dist_udacity.egg-info/SOURCES.txt
dist_udacity.egg-info/dependency_links.txt
dist_udacity.egg-info/not-zip-safe
dist_udacity.egg-info/top_level.txt