Metadata-Version: 1.0
Name: dist-udacity
Version: 0.1
Summary: Gausian & Binomial distributions
Home-page: UNKNOWN
Author: Shabbir Yamani
Author-email: myemail@something.com
License: UNKNOWN
Platform: UNKNOWN
